{
  "kcls-auburn": { "sqft": 20000 },
  "kcls-bellevue": { "sqft": 80000 },
  "kcls-black-diamond": { "sqft": 5000 },
  "kcls-bothell": { "sqft": 22500 },
  "kcls-boulevard-park": { "sqft": 6536 },
  "kcls-burien": { "sqft": 32000 },
  "kcls-carnation": { "sqft": 5000 },
  "kcls-covington": { "sqft": 23000 },
  "kcls-des-moines": { "sqft": 10230 },
  "kcls-duvall": { "sqft": 8000 },
  "kcls-enumclaw": { "sqft": 10541 },
  "kcls-fairwood": { "sqft": 20000 },
  "kcls-fall-city": { "sqft": 5000 },
  "kcls-federal-way": { "sqft": 34500 },
  "kcls-greenbridge": { "sqft": 2300 },
  "kcls-issaquah": { "sqft": 15000 },
  "kcls-kenmore": { "sqft": 10000 },
  "kcls-kent": { "sqft": 22600 },
  "kcls-kent-panther-lake": { "sqft": 5000 },
  "kcls-kingsgate": { "sqft": 10235 },
  "kcls-kirkland": { "sqft": 19500 },
  "kcls-lake-forest-park": { "sqft": 5841 },
  "kcls-lake-hills": { "sqft": 10000 },
  "kcls-maple-valley": { "sqft": 10000 },
  "kcls-mercer-island": { "sqft": 14886 },
  "kcls-muckleshoot": { "sqft": 6000 },
  "kcls-newcastle": { "sqft": 11000 },
  "kcls-newport-way": { "sqft": 8690 },
  "kcls-north-bend": { "sqft": 9600 },
  "kcls-redmond": { "sqft": 30000 },
  "kcls-renton": { "sqft": 19500 },
  "kcls-richmond-beach": { "sqft": 5250 },
  "kcls-sammamish": { "sqft": 19500 },
  "kcls-shoreline": { "sqft": 20954 },
  "kcls-skykomish": { "sqft": 1042 },
  "kcls-skyway": { "sqft": 8000 },
  "kcls-snoqualmie": { "sqft": 6000 },
  "kcls-tukwila": { "sqft": 10000 },
  "kcls-valley-view": { "sqft": 6558 },
  "kcls-vashon": { "sqft": 10000 },
  "kcls-white-center": { "sqft": 10000 },
  "kcls-woodinville": { "sqft": 15000 },
  "kcls-woodmont": { "sqft": 9850 }
}
